flask_ask_alphavideo/__init__.py
flask_ask_alphavideo/cache.py
flask_ask_alphavideo/convert.py
flask_ask_alphavideo/core.py
flask_ask_alphavideo/models.py
flask_ask_alphavideo/verifier.py
Flask_Ask_alphavideo-2.1.0.dist-info/LICENSE.txt
Flask_Ask_alphavideo-2.1.0.dist-info/METADATA
Flask_Ask_alphavideo-2.1.0.dist-info/WHEEL
Flask_Ask_alphavideo-2.1.0.dist-info/top_level.txt
Flask_Ask_alphavideo-2.1.0.dist-info/RECORD
