Metadata-Version: 2.1
Name: Flask-Ask-alphavideo
Version: 2.1.0
Summary: Rapid Alexa Skills Kit Development for Amazon Echo Devices in Python
Home-page: https://github.com/johnwheeler/flask-ask
Author: John Wheeler
Author-email: hello@andrewstech.me
License: Apache 2.0
Platform: any
Classifier: License :: OSI Approved :: Apache Software License
Classifier: Framework :: Flask
Classifier: Programming Language :: Python
Classifier: Environment :: Web Environment
Classifier: Intended Audience :: Developers
Classifier: Operating System :: OS Independent
Classifier: Topic :: Internet :: WWW/HTTP :: Dynamic Content
Classifier: Topic :: Software Development :: Libraries :: Python Modules
Requires-Dist: Flask (==1.1.1)
Requires-Dist: PyYAML (==3.12)
Requires-Dist: six (==1.11.0)
Requires-Dist: Werkzeug (==0.16.1)
Requires-Dist: aniso8601
Requires-Dist: pytube
